atcodertools/__init__.py
atcodertools/atcoder_tools.py
atcodertools/client/__init__.py
atcodertools/client/atcoder.py
atcodertools/client/models/__init__.py
atcodertools/client/models/contest.py
atcodertools/client/models/problem.py
atcodertools/client/models/problem_content.py
atcodertools/client/models/sample.py
atcodertools/client/models/submission.py
atcodertools/codegen/__init__.py
atcodertools/codegen/code_generators/__init__.py
atcodertools/codegen/code_generators/cpp.py
atcodertools/codegen/code_generators/cs.py
atcodertools/codegen/code_generators/custom.py
atcodertools/codegen/code_generators/d.py
atcodertools/codegen/code_generators/go.py
atcodertools/codegen/code_generators/java.py
atcodertools/codegen/code_generators/julia.py
atcodertools/codegen/code_generators/nim.py
atcodertools/codegen/code_generators/python.py
atcodertools/codegen/code_generators/rust.py
atcodertools/codegen/code_generators/swift.py
atcodertools/codegen/code_generators/universal_code_generator.py
atcodertools/codegen/code_generators/universal_generator/cpp.toml
atcodertools/codegen/code_generators/universal_generator/cs.toml
atcodertools/codegen/code_generators/universal_generator/d.toml
atcodertools/codegen/code_generators/universal_generator/go.toml
atcodertools/codegen/code_generators/universal_generator/java.toml
atcodertools/codegen/code_generators/universal_generator/julia.toml
atcodertools/codegen/code_generators/universal_generator/nim.toml
atcodertools/codegen/code_generators/universal_generator/python.toml
atcodertools/codegen/code_generators/universal_generator/rust.toml
atcodertools/codegen/code_generators/universal_generator/swift.toml
atcodertools/codegen/code_style_config.py
atcodertools/codegen/models/__init__.py
atcodertools/codegen/models/code_gen_args.py
atcodertools/codegen/template_engine.py
atcodertools/common/__init__.py
atcodertools/common/judgetype.py
atcodertools/common/language.py
atcodertools/common/logging.py
atcodertools/config/__init__.py
atcoder_tools-2.16.0.dist-info/METADATA
atcoder_tools-2.16.0.dist-info/WHEEL
atcoder_tools-2.16.0.dist-info/entry_points.txt
atcoder_tools-2.16.0.dist-info/licenses/LICENCE
atcoder_tools-2.16.0.dist-info/RECORD
