Metadata-Version: 2.4
Name: atcoder-tools
Version: 2.16.0
Summary: Convenient modules & tools for AtCoder users, written in Python 3.6
License: MIT
License-File: LICENCE
Author: kyuridenamida
Author-email: tyotyo3@gmail.com
Requires-Python: >=3.6,<4.0
Classifier: License :: OSI Approved :: MIT License
Classifier: Programming Language :: Python :: 3
Classifier: Programming Language :: Python :: 3.6
Classifier: Programming Language :: Python :: 3.7
Classifier: Programming Language :: Python :: 3.8
Classifier: Programming Language :: Python :: 3.9
Classifier: Programming Language :: Python :: 3.10
Classifier: Programming Language :: Python :: 3.11
Classifier: Programming Language :: Python :: 3.12
Classifier: Programming Language :: Python :: 3.13
Classifier: Programming Language :: Python :: 3.14
Requires-Dist: Jinja2 (>=2.11.3,<3.0.0)
Requires-Dist: beautifulsoup4 (>=4.9.3,<5.0.0)
Requires-Dist: colorama (>=0.4.4,<0.5.0)
Requires-Dist: markupsafe (==2.0.1)
Requires-Dist: requests (>=2.25.1,<3.0.0)
Requires-Dist: toml (>=0.10.2,<0.11.0)
Project-URL: Documentation, https://github.com/kyuridenamida/atcoder-tools
Project-URL: Repository, https://github.com/kyuridenamida/atcoder-tools
